{
    "type": "FeatureCollection",
    "features": 
    [
        {
            "geometry": {
                "type": "Point",
                "coordinates": [
                    -77.5729012046293,
                    37.64863588569142
                ]
            },
            "type": "Feature",
            "properties": {
                "name": "Access NSM - Richmond",
                "description": "",
                "street": "3941 Deep Rock Rd",
                "city": "Richmond",
                "state": "VA",
                "zip": "23233-1474",
                "notes": "Division: Residential",
                "AM": "",
                "contact": "",
                "phone": "(844) 772-1170 ",
                "email": "alewandowski@nsm-seating.com",
                "website": "",
                "other": "",
                "vaonly": "",
                "freedomnow": "",
                "homeaccess": "",
                "commercial": "",
                "rentals": "",
                "office1": "",
                "office2": "",
                "office3": "",
                "mobile1": "",
                "mobile2": "",
                "mobile3": "",
                "email1": "",
                "email2": "",
                "email3": "",
                "email4": "",
                "hours": "",
                "category": "dealer",
                "HubSpotId": "",
                "EpicorId": "",
                "EpicorNum": "0",
                "storeid": "1"
            }
        },
        {
            "geometry": {
                "type": "Point",
                "coordinates": [
                    -78.74485556101799,
                    42.85401243041932
                ]
            },
            "type": "Feature",
            "properties": {
                "name": "Access NSM - Buffalo",
                "description": "",
                "street": "19B Ransier Drive",
                "city": "West Seneca",
                "state": "NY",
                "zip": "14224-2245",
                "notes": "Division: Residential",
                "AM": "Amanda",
                "contact": "",
                "phone": "716-698-6247",
                "email": "Jason.Barczykowski@nsm-seating.com",
                "website": "",
                "other": "",
                "vaonly": "",
                "freedomnow": "",
                "homeaccess": "",
                "commercial": "",
                "rentals": "",
                "office1": "",
                "office2": "",
                "office3": "",
                "mobile1": "",
                "mobile2": "",
                "mobile3": "",
                "email1": "",
                "email2": "",
                "email3": "",
                "email4": "",
                "hours": "",
                "category": "dealer",
                "HubSpotId": "",
                "EpicorId": "",
                "EpicorNum": "0",
                "storeid": "2"
            }
        },
                {
            "geometry": {
                "type": "Point",
                "coordinates": [
                    -75.80781282233546,
                    41.27473604355055
                ]
            },
            "type": "Feature",
            "properties": {
                "name": "Ameriglide",
                "description": "",
                "street": "1335 Highway 315",
                "city": "Wilkes-barre",
                "state": "PA",
                "zip": "18702",
                "notes": "",
                "AM": "",
                "contact": "",
                "phone": "570.634.5438",
                "email": "cliffmailloux@gmail.com",
                "website": "",
                "other": "",
                "vaonly": "",
                "freedomnow": "",
                "homeaccess": "",
                "commercial": "",
                "rentals": "",
                "office1": "",
                "office2": "",
                "office3": "",
                "mobile1": "",
                "mobile2": "",
                "mobile3": "",
                "email1": "",
                "email2": "",
                "email3": "",
                "email4": "",
                "hours": "",
                "category": "dealer",
                "HubSpotId": "",
                "EpicorId": "",
                "EpicorNum": "0",
                "storeid": "13"
            }
        }
    ]
}
